{
	"info": {
		"_postman_id": "a3f78501-4e3d-4380-82f4-f905a476bb23",
		"name": "Stock Tracker",
		"schema": "https://schema.getpostman.com/json/collection/v2.1.0/collection.json"
	},
	"item": [
		{
			"name": "/stock",
			"request": {
				"method": "POST",
				"header": [],
				"url": {
					"raw": "http://localhost:8080/stock",
					"protocol": "http",
					"host": [
						"localhost"
					],
					"port": "8080",
					"path": [
						"stock"
					]
				}
			},
			"response": []
		},
		{
			"name": "/stock/{id}",
			"request": {
				"method": "DELETE",
				"header": [],
				"url": {
					"raw": "http://localhost:8080/stock/1",
					"protocol": "http",
					"host": [
						"localhost"
					],
					"port": "8080",
					"path": [
						"stock",
						"1"
					]
				}
			},
			"response": []
		},
		{
			"name": "/stock",
			"request": {
				"method": "GET",
				"header": [],
				"url": {
					"raw": "http://localhost:8080/stock",
					"protocol": "http",
					"host": [
						"localhost"
					],
					"port": "8080",
					"path": [
						"stock"
					]
				}
			},
			"response": []
		},
		{
			"name": "/stock?id=x",
			"request": {
				"method": "GET",
				"header": [],
				"url": {
					"raw": "http://localhost:8080/stock?id=1",
					"protocol": "http",
					"host": [
						"localhost"
					],
					"port": "8080",
					"path": [
						"stock"
					],
					"query": [
						{
							"key": "id",
							"value": "1"
						}
					]
				}
			},
			"response": []
		},
		{
			"name": "/stock",
			"request": {
				"method": "PUT",
				"header": [],
				"body": {
					"mode": "raw",
					"raw": " {\n        \"id\": 2,\n        \"name\": \"Laptop\",\n        \"quantity\": 50,\n        \"boughtPrice\": 25000.0,\n        \"sellPrice\": 35000.0,\n        \"stockCode\": 45454545,\n        \"barcode\": 5445445,\n        \"unitId\": 2\n    }",
					"options": {
						"raw": {
							"language": "json"
						}
					}
				},
				"url": {
					"raw": "http://localhost:8080/stock",
					"protocol": "http",
					"host": [
						"localhost"
					],
					"port": "8080",
					"path": [
						"stock"
					]
				}
			},
			"response": []
		},
		{
			"name": "/unit",
			"request": {
				"method": "GET",
				"header": [],
				"url": null
			},
			"response": []
		},
		{
			"name": "/unit",
			"request": {
				"method": "GET",
				"header": [],
				"url": null
			},
			"response": []
		}
	]
}